{
  "updates": [
    {
      "date": "2024-01-23",
      "version": "Latest Update",
      "changes": [
        {
          "item": "Test Item 1",
          "oldValue": 100,
          "newValue": 150,
          "type": "value_change"
        },
        {
          "item": "Test Item 2",
          "oldValue": 200,
          "newValue": 250,
          "type": "value_change"
        }
      ]
    },
    {
      "date": "2024-01-23",
      "version": "Last Update",
      "changes": [
        {
          "item": "Test Item 3",
          "oldValue": 300,
          "newValue": 350,
          "type": "value_change"
        }
      ]
    }
  ]
}
